{
  "fabric:load_conditions": [
    {
      "condition": "fabric:all_mods_loaded",
      "values": ["create"]
    }
  ],
  "neoforge:conditions": [
    {
      "type": "neoforge:mod_loaded",
      "modid": "create"
    }
  ],
  "type": "create:mixing",
  "group": "spawn_egg",
  "ingredients": [
    {
      "item": "minecraft:zombie_spawn_egg"
    },
    {
      "item": "minecraft:rotten_flesh"
    },
    [
      {
        "item": "minecraft:iron_ingot"
      },
      {
        "item": "minecraft:gold_ingot"
      }
    ],
    {
      "item": "minecraft:copper_ingot"
    },
    {
      "item": "minecraft:seagrass"
    },
    {
      "item": "minecraft:slime_ball"
    },
    {
      "item": "minecraft:ghast_tear"
    },
    {
      "item": "minecraft:trident"
    },
    {
      "type": "fluid_stack",
      "amount": 500,
      "fluid": "minecraft:water"
    }
  ],
  "results": [
    {
      "id": "minecraft:drowned_spawn_egg"
    }
  ]
}